CodeIntel-2.0.0.dist-info/DESCRIPTION.rst
CodeIntel-2.0.0.dist-info/METADATA
CodeIntel-2.0.0.dist-info/RECORD
CodeIntel-2.0.0.dist-info/WHEEL
CodeIntel-2.0.0.dist-info/entry_points.txt
CodeIntel-2.0.0.dist-info/metadata.json
CodeIntel-2.0.0.dist-info/top_level.txt
codeintel/HTMLTreeParser.py
codeintel/__init__.py
codeintel/__main__.py
codeintel/_cElementTree.cp35-win32.pyd
codeintel/_ciElementTree.cp35-win32.pyd
codeintel/benchmark.py
codeintel/cElementTree.py
codeintel/ci2.py
codeintel/ciElementTree.py
codeintel/ciperf.py
codeintel/cix2html.py
codeintel/client.py
codeintel/ctypesutils.py
codeintel/difflibex.py
codeintel/directoryServiceUtils.py
codeintel/eollib.py
codeintel/fileutils.py
codeintel/koCatalog.py
codeintel/koDTD.py
codeintel/koRNGElementTree.py
codeintel/koSimpleLexer.py
codeintel/koTreeView.p.py
codeintel/koUnicodeEncoding.py
codeintel/koXMLDatasetInfo.py
codeintel/koXMLPrefs.py
codeintel/koXMLTreeService.py
codeintel/koprocessutils.py
codeintel/kotaclib.py
codeintel/langinfo.py
codeintel/langinfo_binary.py
codeintel/langinfo_doc.py
codeintel/langinfo_go.py
codeintel/langinfo_komodo.py
codeintel/langinfo_mozilla.py
codeintel/langinfo_mxml.py
codeintel/langinfo_other.py
codeintel/langinfo_prog.py
codeintel/langinfo_template.py
codeintel/langinfo_tiny.py
codeintel/memutils.py
codeintel/mozutils.py
codeintel/process.py
codeintel/pythonVersionUtils.py
codeintel/pyxpcomProfiler.py
codeintel/reflow.py
codeintel/sgmlop.cp35-win32.pyd
codeintel/sitepyxpcom.py
codeintel/stacktracer.py
codeintel/strptime.py
codeintel/styles.py
codeintel/textinfo.py
codeintel/textutils.py
codeintel/thread_helper.py
codeintel/upgradeutils.py
codeintel/uriparse.py
codeintel/which.py
codeintel/win32_named_pipe.py
codeintel/wininteg.py
codeintel/winprocess.py
codeintel/SilverCity/CPP.py
codeintel/SilverCity/CSS.py
codeintel/SilverCity/DispatchHandler.py
codeintel/SilverCity/HTMLGenerator.py
codeintel/SilverCity/HyperText.py
codeintel/SilverCity/JavaScript.py
codeintel/SilverCity/Keywords.py
codeintel/SilverCity/LanguageInfo.py
codeintel/SilverCity/Lexer.py
codeintel/SilverCity/NULL.py
codeintel/SilverCity/Perl.py
codeintel/SilverCity/PostScript.py
