Metadata-Version: 2.0
Name: CodeIntel
Version: 2.0.0
Summary: Komodo Edit CodeIntel
Home-page: https://github.com/SublimeCodeIntel/CodeIntel
Author: German Mendez Bravo (Kronuz)
Author-email: german.mb@gmail.com
License: MPL 1.1
Keywords: codeintel intellisense autocomplete ide languages python go javascript mason xbl xul rhtml scss python html ruby python3 xml sass xslt django html5 perl css twig less smarty node tcl templatetoolkit php
Platform: UNKNOWN
Classifier: License :: OSI Approved :: Mozilla Public License 1.1 (MPL 1.1)
Classifier: Development Status :: 4 - Beta
Classifier: Programming Language :: Python
Classifier: Programming Language :: Python :: 2
Classifier: Programming Language :: Python :: 2.7
Classifier: Programming Language :: Python :: 3
Classifier: Programming Language :: Python :: 3.3
Classifier: Programming Language :: Python :: 3.4
Classifier: Programming Language :: Python :: 3.5
Classifier: Programming Language :: Python :: 3.6
Requires-Dist: 3to2
Requires-Dist: applib
Requires-Dist: chardet
Requires-Dist: cmdln
Requires-Dist: esprima
Requires-Dist: inflector
Requires-Dist: libclang-py3
Requires-Dist: six
Requires-Dist: zope.cachedescriptors
